{
  "products": [
    {
      "id": 1,
      "name": "Iphone X",
      "price": "32",
      "status": true
    },
    {
      "name": "Samsung Galaxy S10",
      "price": 700,
      "status": false,
      "id": 2
    },
    {
      "name": "Khoai tây",
      "price": "1000",
      "status": true,
      "id": 6
    },
    {
      "id": 7,
      "name": "bánh mì",
      "price": "180000",
      "status": false
    },
    {
      "id": 8,
      "name": "Rau xà lách sống 8787",
      "price": "180000",
      "status": true
    }
  ]
}